LICENSE.txt
README.rst
setup.py
alteon2f5/__init__.py
alteon2f5/alteon2f5.py
alteon2f5.egg-info/PKG-INFO
alteon2f5.egg-info/SOURCES.txt
alteon2f5.egg-info/dependency_links.txt
alteon2f5.egg-info/top_level.txt