Metadata-Version: 2.1
Name: alteon2f5
Version: 1.4
Summary: A Python script to convert Alteon configuration to F5 syntax
Home-page: https://pypi.python.org/pypi?:action=display&name=alteon2f5&version=1.2
Author: Pete White
Author-email: pwhite@f5.com
License: PSF
Platform: UNKNOWN
License-File: LICENSE.txt
